skfp/__init__.py
skfp/applicability_domain/__init__.py
skfp/applicability_domain/bounding_box.py
skfp/applicability_domain/convex_hull.py
skfp/applicability_domain/distance_to_centroid.py
skfp/applicability_domain/hotelling_t2_test.py
skfp/applicability_domain/knn.py
skfp/applicability_domain/leverage.py
skfp/applicability_domain/pca_bounding_box.py
skfp/applicability_domain/prob_std.py
skfp/applicability_domain/response_variable_range.py
skfp/applicability_domain/standard_deviation.py
skfp/applicability_domain/topkat.py
skfp/bases/__init__.py
skfp/bases/base_ad_checker.py
skfp/bases/base_filter.py
skfp/bases/base_fp_transformer.py
skfp/bases/base_preprocessor.py
skfp/bases/base_substructure_filter.py
skfp/bases/base_substructure_fp.py
skfp/datasets/__init__.py
skfp/datasets/lrgb/__init__.py
skfp/datasets/lrgb/benchmark.py
skfp/datasets/lrgb/peptides_func.py
skfp/datasets/lrgb/peptides_struct.py
skfp/datasets/moleculeace/__init__.py
skfp/datasets/moleculeace/benchmark.py
skfp/datasets/moleculeace/moleculeace.py
skfp/datasets/moleculenet/__init__.py
skfp/datasets/moleculenet/bace.py
skfp/datasets/moleculenet/bbbp.py
skfp/datasets/moleculenet/benchmark.py
skfp/datasets/moleculenet/clintox.py
skfp/datasets/moleculenet/esol.py
skfp/datasets/moleculenet/freesolv.py
skfp/datasets/moleculenet/hiv.py
skfp/datasets/moleculenet/lipophilicity.py
skfp/datasets/moleculenet/muv.py
skfp/datasets/moleculenet/pcba.py
skfp/datasets/moleculenet/sider.py
skfp/datasets/moleculenet/tox21.py
skfp/datasets/moleculenet/toxcast.py
skfp/datasets/tdc/__init__.py
skfp/datasets/tdc/adme.py
skfp/datasets/tdc/benchmark.py
skfp/datasets/tdc/hts.py
skfp/datasets/tdc/tox.py
skfp/datasets/utils.py
skfp/descriptors/__init__.py
skfp/descriptors/charge.py
skfp/descriptors/constitutional.py
skfp/descriptors/topological.py
skfp/distances/__init__.py
skfp/distances/braun_blanquet.py
skfp/distances/ct4.py
skfp/distances/dice.py
skfp/distances/fraggle.py
skfp/distances/harris_lahey.py
scikit_fingerprints-1.18.0.dist-info/WHEEL
scikit_fingerprints-1.18.0.dist-info/METADATA
scikit_fingerprints-1.18.0.dist-info/RECORD
