Metadata-Version: 2.3
Name: scikit-fingerprints
Version: 1.18.0
Summary: Library for effective molecular fingerprints calculation
Keywords: molecular fingerprints,molecular descriptors,chemoinformatics,chemistry,machine learning
Author: AGH ML & Chemoinformatics Group
Author-email: AGH ML & Chemoinformatics Group <jadamczy@agh.edu.pl>
License: MIT
Classifier: Intended Audience :: Information Technology
Classifier: Intended Audience :: Science/Research
Classifier: License :: OSI Approved :: MIT License
Classifier: Programming Language :: Python :: 3.10
Classifier: Programming Language :: Python :: 3.11
Classifier: Programming Language :: Python :: 3.12
Classifier: Programming Language :: Python :: 3.13
Classifier: Topic :: Scientific/Engineering :: Artificial Intelligence
Classifier: Topic :: Scientific/Engineering :: Bio-Informatics
Classifier: Topic :: Scientific/Engineering :: Chemistry
Classifier: Topic :: Scientific/Engineering :: Medical Science Apps.
Classifier: Topic :: Software Development :: Libraries :: Python Modules
Classifier: Typing :: Typed
Requires-Dist: descriptastorus>=2.0.0,<3
Requires-Dist: e3fp>=1.2.6,<2
Requires-Dist: huggingface-hub<1
Requires-Dist: joblib>=1.0.0,<2
Requires-Dist: mordredcommunity>=2.0.0,<3
Requires-Dist: numba<1
Requires-Dist: numpy>=1.20.0,<3
Requires-Dist: pandas<3
Requires-Dist: rdkit<=2025.3.6
Requires-Dist: scikit-learn>=1.0.0,<2
Requires-Dist: scipy>=1.0.0,<2
Requires-Dist: tqdm>=4.0.0,<5
Requires-Python: >=3.10, <3.14
Project-URL: Bug Tracker, https://github.com/scikit-fingerprints/scikit-fingerprints/issues
Project-URL: documentation, https://scikit-fingerprints.readthedocs.io/latest
Project-URL: homepage, https://github.com/scikit-fingerprints/scikit-fingerprints
Project-URL: repository, https://github.com/scikit-fingerprints/scikit-fingerprints
